[
  {
    "i": 9784000071420,
    "t": "\u660e\u60e0\u4e0a\u4eba\u96c6",
    "h": 1,
    "e": 0
  },
  {
    "i": 9784000077323,
    "t": "Zo\u0304ki ishoku 48-jikan",
    "h": 1,
    "e": 0
  },
  {
    "i": 9784032073300,
    "t": "\u304a\u3084\u3064\u306f\u306a\u3042\u306b?",
    "h": 1,
    "e": 0
  },
  {
    "i": 9784039070708,
    "t": "Sekai no mukashi banashi : ichinensei",
    "h": 1,
    "e": 0
  },
  {
    "i": 9784041576137,
    "t": "\u4e80\u88c2",
    "h": 1,
    "e": 0
  },
  {
    "i": 9784041576168,
    "t": "Misshitsu satsujin jiken : misuteri\u0304 ansoroji\u0304",
    "h": 1,
    "e": 0
  },
  {
    "i": 9784041579244,
    "t": "Imite\u0304shon go\u0304rudo",
    "h": 1,
    "e": 0
  },
  {
    "i": 9784062070515,
    "t": "Satsujin no supotto raito",
    "h": 1,
    "e": 0
  },
  {
    "i": 9784062070997,
    "t": "\u3082\u3046\u3059\u3050\u5973\u3056\u304b\u308a : \u4eba\u751f\u5909\u3048\u3069\u304d\u5909\u308f\u308a\u3069\u304d",
    "h": 1,
    "e": 0
  },
  {
    "i": 9784062071406,
    "t": "\u30b7\u30e7\u30fc\u30fb\u30b3\u30b9\u30ae\u306e\u904b\u3092\u6451\u3080 = One way ticket to success",
    "h": 1,
    "e": 0
  },
  {
    "i": 9784062071833,
    "t": "Misuteri\u0304zu",
    "h": 1,
    "e": 0
  },
  {
    "i": 9784062072274,
    "t": "\"\u540d\u533b\u304c\u6559\u3048\u308b\" \u3053\u3093\u306a\u75c7\u72b6\u306f\u3059\u3050\u75c5\u9662\u3078\u884c\u3051",
    "h": 1,
    "e": 0
  },
  {
    "i": 9784062073073,
    "t": "\u4e2d\u68ee\u660e\u83dc \u54c0\u3057\u3044\u6027(\u3055\u304c)",
    "h": 1,
    "e": 0
  },
  {
    "i": 9784062073547,
    "t": "Waratte daio\u0304jo\u0304",
    "h": 1,
    "e": 0
  },
  {
    "i": 9784062073912,
    "t": "Hyo\u0304kai no genjitsu",
    "h": 1,
    "e": 0
  },
  {
    "i": 9784062074155,
    "t": "\u6c7a\u5b9a\u7248\u8b1b\u9053\u9928\u67d4\u9053",
    "h": 1,
    "e": 0
  },
  {
    "i": 9784062074582,
    "t": "Dancing in the sky",
    "h": 1,
    "e": 0
  },
  {
    "i": 9784062075381,
    "t": "\u60e8\u5287\u306e\u30a2\u30c6\u30ca\u30a4",
    "h": 1,
    "e": 0
  },
  {
    "i": 9784062075732,
    "t": "Yamato o aruku : suiboku kiko\u0304",
    "h": 1,
    "e": 0
  },
  {
    "i": 9784062076227,
    "t": "Meisaku o kaita onnatachi : jibun o ikita 13-nin no jinsei : Agatha Christie ... [et al.]",
    "h": 1,
    "e": 0
  },
  {
    "i": 9784062077255,
    "t": "\u9244\u306e\u82b1\u3092\u633f\u3059\u8005",
    "h": 1,
    "e": 0
  },
  {
    "i": 9784062077453,
    "t": "\u5947\u8de1\u306e\u30db\u30eb\u30e2\u30f3\u30e1\u30e9\u30c8\u30cb\u30f3",
    "h": 1,
    "e": 0
  },
  {
    "i": 9784062078023,
    "t": "\u79c0\u5409\u3068\u304a\u306d",
    "h": 1,
    "e": 0
  },
  {
    "i": 9784062079082,
    "t": "\u751f\u304d\u3066\u3044\u308b\u6d77 : \u6771\u4eac\u6e7e",
    "h": 1,
    "e": 1
  },
  {
    "i": 9784062570145,
    "t": "Koko ga shiritai hando\u0304tai",
    "h": 1,
    "e": 0
  },
  {
    "i": 9784062570411,
    "t": "Doko made tokeru Nihon no sanpo\u0304 : wasan de atama no tore\u0304ningu",
    "h": 1,
    "e": 0
  },
  {
    "i": 9784098070053,
    "t": "\u3057\u3064\u3051\u56f3\u89e3\u4e8b\u5178 : \u3057\u3064\u3051\u304c\u8eab\u306b\u4ed8\u3051\u3070, \u5b66\u529b\u3082\u30a2\u30c3\u30d7!",
    "h": 1,
    "e": 0
  },
  {
    "i": 9784102070116,
    "t": "\u8679. \u4e0b\u5377",
    "h": 1,
    "e": 0
  },
  {
    "i": 9784140071540,
    "t": "Dokyumento BBC o\u0304koku no ho\u0304kai",
    "h": 1,
    "e": 0
  },
  {
    "i": 9784152075772,
    "t": "\u30b4\u30c3\u30c9\u30a6\u30eb\u30d5\u306e\u884c\u65b9",
    "h": 1,
    "e": 0
  },
  {
    "i": 9784152076588,
    "t": "Akushidentaru tsu\u0304risuto",
    "h": 1,
    "e": 0
  },
  {
    "i": 9784152076847,
    "t": "Roshia hausu",
    "h": 1,
    "e": 0
  },
  {
    "i": 9784261071597,
    "t": "Kaiso\u0304 to zuiso\u0304",
    "h": 1,
    "e": 0
  },
  {
    "i": 9784274071744,
    "t": "No\u0304gaku, seibutsugaku no tame no konpyu\u0304ta o\u0304yo\u0304",
    "h": 1,
    "e": 0
  },
  {
    "i": 9784274073533,
    "t": "\u77e5\u8b58\u5de5\u5b66",
    "h": 1,
    "e": 0
  },
  {
    "i": 9784274075612,
    "t": "\u30b7\u30b9\u30c6\u30e0\u306e\u4f01\u753b\u3068\u8a2d\u8a08",
    "h": 1,
    "e": 0
  },
  {
    "i": 9784274076138,
    "t": "\u30b7\u30b9\u30c6\u30e0\u306e\u76e3\u67e5",
    "h": 1,
    "e": 0
  },
  {
    "i": 9784306071476,
    "t": "Yo\u0304chi hosho\u0304 no tebiki",
    "h": 1,
    "e": 0
  },
  {
    "i": 9784307070034,
    "t": "Sotsuzen kyo\u0304iku no tame no ho\u0304shasen shindangaku",
    "h": 1,
    "e": 0
  },
  {
    "i": 9784307070157,
    "t": "Shokudo\u0304 shikkan gazo\u0304 shindangaku",
    "h": 1,
    "e": 0
  },
  {
    "i": 9784307070164,
    "t": "Jiki kyo\u0304mei gazo\u0304 shindangaku",
    "h": 1,
    "e": 0
  },
  {
    "i": 9784307070171,
    "t": "Saishin rinsho\u0304 kakuigaku",
    "h": 1,
    "e": 0
  },
  {
    "i": 9784307070195,
    "t": "Ho\u0304shasen shinryo\u0304 yo\u0304goshu\u0304 = Japan Radiological Society terminology",
    "h": 1,
    "e": 0
  },
  {
    "i": 9784307070201,
    "t": "SPECT no rinsho\u0304 = Single photon emission computed tomography",
    "h": 1,
    "e": 0
  },
  {
    "i": 9784307070218,
    "t": "Zukai gazo\u0304 kaibo\u0304gaku",
    "h": 1,
    "e": 0
  },
  {
    "i": 9784307070225,
    "t": "Ho\u0304shasen shindan gijutsu no chiryo\u0304teki o\u0304yo\u0304 = Interventioal radiology",
    "h": 1,
    "e": 0
  },
  {
    "i": 9784307070232,
    "t": "Jitchi ika no tame no i x-sen dokuei no wan pointo adobaisu",
    "h": 1,
    "e": 0
  },
  {
    "i": 9784307070249,
    "t": "Atarashii shinzo\u0304 kaku igaku",
    "h": 1,
    "e": 0
  },
  {
    "i": 9784307070256,
    "t": "Ichimai no x-sen shashin kara : kanbetsu shindan no susumekata to kangaekata",
    "h": 1,
    "e": 0
  },
  {
    "i": 9784307070270,
    "t": "Sho\u0304kakan shindan'yo X-sen so\u0304chi no tame no sanran X-sen jokyoyo\u0304 guriddo no kiso",
    "h": 1,
    "e": 0
  },
  {
    "i": 9784307070287,
    "t": "Wakariyasui kyo\u0304bu x-sen shashin no dokueiho\u0304 : kanbetsu shindan no tame ni",
    "h": 1,
    "e": 0
  },
  {
    "i": 9784307070300,
    "t": "Sui CT ERCP dokuei no jissai",
    "h": 1,
    "e": 0
  },
  {
    "i": 9784307070317,
    "t": "Chu\u0304su\u0304 shinkei shikkan no MR shindan",
    "h": 1,
    "e": 0
  },
  {
    "i": 9784307070331,
    "t": "Zo\u0304eizai manyuaru",
    "h": 1,
    "e": 0
  },
  {
    "i": 9784307070416,
    "t": "IVR : interventional radiology = Ho\u0304shasen shindan gijutsu no chiryo\u0304teki o\u0304yo\u0304",
    "h": 1,
    "e": 0
  },
  {
    "i": 9784320071179,
    "t": "Hatsumei handobukku",
    "h": 1,
    "e": 0
  },
  {
    "i": 9784334070311,
    "t": "Shikabane-ran : Shinjuku-zame III",
    "h": 1,
    "e": 0
  },
  {
    "i": 9784334070342,
    "t": "\u6df8\u5c11\u7d0d\u8a00\u6bba\u4eba\u4e8b\u4ef6 : \u9577\u7de8\u63a8\u7406\u5c0f\u8aaa",
    "h": 1,
    "e": 0
  },
  {
    "i": 9784338072045,
    "t": "Nagai rusuban dekiru ka no",
    "h": 1,
    "e": 0
  },
  {
    "i": 9784339070552,
    "t": "Iyo\u0304 gazo\u0304 shindan so\u0304chi : CT, MRI o chu\u0304shin to shite",
    "h": 1,
    "e": 0
  },
  {
    "i": 9784339070569,
    "t": "Seitai shingo\u0304 : keisoku to kaiseki no jissai",
    "h": 1,
    "e": 0
  },
  {
    "i": 9784339070576,
    "t": "Ho\u0304shasen kiki ko\u0304gaku",
    "h": 1,
    "e": 0
  },
  {
    "i": 9784339070590,
    "t": "Rinsho\u0304 ko\u0304gaku gishi no tame no iyo\u0304 keisoku gijutsu",
    "h": 1,
    "e": 0
  },
  {
    "i": 9784339076806,
    "t": "Atarashii shokubutsu o tsukuru : shokubutsu baiotekunoroji\u0304 no sekai",
    "h": 1,
    "e": 0
  },
  {
    "i": 9784340073023,
    "t": "\u3088\u304f\u3042\u305f\u308b\u30c8\u30e9\u30f3\u30d7\u306a\u3093\u3067\u3082\u5360\u3044",
    "h": 1,
    "e": 0
  },
  {
    "i": 9784341070021,
    "t": "\u8133\u5352\u4e2d\u306f\u98df\u5353\u306b\u3042\u308a",
    "h": 1,
    "e": 0
  },
  {
    "i": 9784341070038,
    "t": "\u7cd6\u5c3f\u306f\u75c5\u6c17\u3067\u306f\u306a\u3044",
    "h": 1,
    "e": 0
  },
  {
    "i": 9784341070045,
    "t": "\u809d\u81d3\u306b\u3082\u3063\u3068\u611f\u8b1d\u3092!",
    "h": 1,
    "e": 0
  },
  {
    "i": 9784341070083,
    "t": "\u30ac\u30c3\u30c4\u3067\u6cbb\u305d\u3046\u80c3\u8178\u75c5",
    "h": 1,
    "e": 0
  },
  {
    "i": 9784341070090,
    "t": "\"\u3046\u3064\"\u3068\u4e0a\u624b\u306b\u3064\u304d\u3042\u3046",
    "h": 1,
    "e": 0
  },
  {
    "i": 9784341070106,
    "t": "\u814e\u81d3\u306f\u3084\u3055\u3057\u3055\u3092\u5f85\u3063\u3066\u3044\u308b",
    "h": 1,
    "e": 0
  },
  {
    "i": 9784341070144,
    "t": "\u7720\u308a\u305f\u3044 \u7720\u308c\u306a\u3044 \u4e0d\u7720\u306f\u6c17\u304b\u3089",
    "h": 1,
    "e": 0
  },
  {
    "i": 9784341070151,
    "t": "\u8170\u75db\u306f, \u6b65\u3051 \u52d5\u3051",
    "h": 1,
    "e": 0
  },
  {
    "i": 9784341070168,
    "t": "\u5148\u624b\u3067\u5b89\u5fc3\u9ad8\u8840\u5727",
    "h": 1,
    "e": 0
  },
  {
    "i": 9784341070182,
    "t": "\u6b6f\u306f\u305f\u3044\u305b\u3064\u306a\u81d3\u5668\u306e\u3072\u3068\u3064",
    "h": 1,
    "e": 0
  },
  {
    "i": 9784341070243,
    "t": "\u6575\u306f\"\u80f8\"\u306b\u3042\u308a \u5fc3\u7b4b\u6897\u585e\u30fb\u72ed\u5fc3\u75c7",
    "h": 1,
    "e": 0
  },
  {
    "i": 9784381071293,
    "t": "\u56f2\u7881\u8a70\u7881\u96c6",
    "h": 1,
    "e": 0
  },
  {
    "i": 9784381075468,
    "t": "\u30aa\u30fc\u30c8\u30de\u30c1\u30c3\u30af\u8eca\u306e\u30c9\u30e9\u30a4\u30d3\u30f3\u30b0 = AT car-driving",
    "h": 1,
    "e": 0
  },
  {
    "i": 9784381075864,
    "t": "AT\u8eca\u8def\u4e0a\u30c9\u30e9\u30a4\u30d3\u30f3\u30b0",
    "h": 1,
    "e": 0
  },
  {
    "i": 9784381076199,
    "t": "\u81ea\u52d5\u8eca\u30d9\u30fc\u30b7\u30c3\u30af\u56f3\u9451",
    "h": 1,
    "e": 0
  },
  {
    "i": 9784381076816,
    "t": "\u5e83\u7530\u6d41\u3053\u3060\u308f\u308a\u30ab\u30fc\u30e1\u30f3\u30c6\u30ca\u30f3\u30b9\u30d0\u30a4\u30d6\u30eb : \u30e6\u30fc\u30b6\u30fc\u8eca\u691c\u5408\u683c\u6cd5\u5b8c\u5168\u89e3\u8aaa!!",
    "h": 1,
    "e": 0
  },
  {
    "i": 9784381076953,
    "t": "\u624b\u8a18\u30a2\u30a4\u30eb\u30c8\u30f3\u30fb\u30bb\u30ca = Ayrton Senna",
    "h": 1,
    "e": 0
  },
  {
    "i": 9784381077011,
    "t": "\u521d\u5fc3\u8005\u3067\u3082\u7c21\u5358\u306b\u3067\u304d\u308b\u65e5\u66dc\u30ab\u30fc\u30e1\u30f3\u30c6\u30ca\u30f3\u30b9",
    "h": 1,
    "e": 0
  },
  {
    "i": 9784386570012,
    "t": "Bosuton no yo wa fukete : sentan gijutsu shiron",
    "h": 1,
    "e": 0
  }
]