[
  {
    "i": 9787010002354,
    "t": "Guangdong nong min yun dong jiang xi suo zi liao xuan bian",
    "h": 1,
    "e": 1
  },
  {
    "i": 9787010004396,
    "t": "Zhuang zu = Bouxcuengh",
    "h": 1,
    "e": 0
  },
  {
    "i": 9787010004952,
    "t": "\u4eba\u6c11\u653f\u534f\u77e5\u8bc6\u624b\u518c",
    "h": 1,
    "e": 0
  },
  {
    "i": 9787020000609,
    "t": "Chi yuen",
    "h": 1,
    "e": 1
  },
  {
    "i": 9787020003082,
    "t": "Buxijin shu jing shi xuan",
    "h": 1,
    "e": 1
  },
  {
    "i": 9787020004294,
    "t": "Lafengdan yu yan shi hsuan",
    "h": 1,
    "e": 1
  },
  {
    "i": 9787020004478,
    "t": "Ming zuo jia xie di tong hua gu shi",
    "h": 1,
    "e": 0
  },
  {
    "i": 9787020006809,
    "t": "Xie ji nan ren di qing shi : dang dai qing nian nu\u0308 shi ren ai qing shi xuan",
    "h": 1,
    "e": 1
  },
  {
    "i": 9787020008667,
    "t": "\u795e\u66f2 : \u5730\u72f1\u7bc7",
    "h": 1,
    "e": 1
  },
  {
    "i": 9787020009169,
    "t": "Meng chou",
    "h": 1,
    "e": 1
  },
  {
    "i": 9787030000941,
    "t": "Hu hsi li hsu\u0308eh",
    "h": 1,
    "e": 1
  },
  {
    "i": 9787030001207,
    "t": "Chang liang : li long he ying yong",
    "h": 1,
    "e": 1
  },
  {
    "i": 9787030004178,
    "t": "\u79d1\u5b78\u6280\u672e\u767e\u79d1\u5168\u4e66",
    "h": 1,
    "e": 1
  },
  {
    "i": 9787030009135,
    "t": "\u4e2d\u56fd\u6cbc\u6cfd\u7814\u7a76",
    "h": 1,
    "e": 1
  },
  {
    "i": 9787100008419,
    "t": "2001 and beyond",
    "h": 1,
    "e": 1
  },
  {
    "i": 9787102000770,
    "t": "\u5510\u6479\u842c\u6b72\u901a\u5929\u5e16 : \u8fbd\u5b81\u7701\u535a\u7269\u9986\u85cf\u58a8\u8ff9",
    "h": 1,
    "e": 1
  },
  {
    "i": 9787102007168,
    "t": "\u694a\u4ef2\u5b50\u91d1\u77f3\u907a\u7a3f",
    "h": 1,
    "e": 0
  },
  {
    "i": 9787103002063,
    "t": "Chang yong wu dao dong zuo xuan",
    "h": 1,
    "e": 0
  },
  {
    "i": 9787103006429,
    "t": "Gang qin cu bu jiao cheng xin bian",
    "h": 1,
    "e": 1
  },
  {
    "i": 9787104002604,
    "t": "Yu long mei hao ke",
    "h": 1,
    "e": 1
  },
  {
    "i": 9787104004455,
    "t": "\u6232\u8ff7\u5fc5\u5907. \u8001\u65e6\u4eac\u5267\u6d41\u6d3e\u5531\u6bb5\u835f\u8403",
    "h": 1,
    "e": 0
  },
  {
    "i": 9787104006060,
    "t": "\u95f4\u8c0d\u6218\u79d8\u53f2",
    "h": 1,
    "e": 0
  },
  {
    "i": 9787105004065,
    "t": "Siyasi iqtisat lughiti",
    "h": 1,
    "e": 1
  },
  {
    "i": 9787105007530,
    "t": "Na\u0306za\u0306riya\u0306 o\u0308ginish lughiti",
    "h": 1,
    "e": 1
  },
  {
    "i": 9787105007608,
    "t": "A\u0306da\u0306biyat ha\u0306qqida omumii bayat",
    "h": 1,
    "e": 0
  },
  {
    "i": 9787105008346,
    "t": "Ai di jiang shang",
    "h": 1,
    "e": 0
  },
  {
    "i": 9787105008476,
    "t": "O\u0308chma\u0306s gu\u0308lkhan",
    "h": 1,
    "e": 0
  },
  {
    "i": 9787105008506,
    "t": "Fa\u0304rsi\u0304 = Ji chu Bosi yu = Pars tilidin savat",
    "h": 1,
    "e": 1
  },
  {
    "i": 9787105008506,
    "t": "\u57fa\u7840\u6ce2\u65af\u8bed",
    "h": 1,
    "e": 1
  },
  {
    "i": 9787106000127,
    "t": "Huo xia qu : Heize Ming dian ying ju ben xuan ji",
    "h": 1,
    "e": 1
  },
  {
    "i": 9787106001803,
    "t": "\u5b9a\u9675\u5730\u5bae",
    "h": 1,
    "e": 0
  },
  {
    "i": 9787108004352,
    "t": "Hafo jing li xue yuan chi\u0301n li ji : Ru he che\u0301ng wei gao ji guan li ren yuan",
    "h": 1,
    "e": 1
  },
  {
    "i": 9787109000018,
    "t": "Zhongguo cheng jiao jing ji fa zhan xin fang xiang",
    "h": 1,
    "e": 1
  },
  {
    "i": 9787110003596,
    "t": "\u755c\u79bd\u5e38\u89c1\u75c5\u7684\u9632\u6cbb",
    "h": 1,
    "e": 1
  },
  {
    "i": 9787110005170,
    "t": "\u5916\u8d38\u5916\u4e8b\u57fa\u672c\u77e5\u8bc6",
    "h": 1,
    "e": 1
  },
  {
    "i": 9787110007860,
    "t": "\u9999\u8549\u683d\u57f9\u6280\u672e",
    "h": 1,
    "e": 0
  },
  {
    "i": 9787110008492,
    "t": "\u94a2\u7b14\u4e66\u6cd5\u5b57\u5178 : \u771f\u8349\u96b6\u7bc6",
    "h": 1,
    "e": 1
  },
  {
    "i": 9787112007578,
    "t": "Zhongguo xian dai bao jian ke xue",
    "h": 1,
    "e": 1
  },
  {
    "i": 9787113007256,
    "t": "\u901a\u970d\u7ebf\u7eaa\u884c",
    "h": 1,
    "e": 0
  },
  {
    "i": 9787113007720,
    "t": "\u8861\u5e7f\u98ce\u4e91",
    "h": 1,
    "e": 0
  },
  {
    "i": 9787113009694,
    "t": "\u5317\u4eac\u65c5\u884c\u6307\u5357",
    "h": 1,
    "e": 0
  },
  {
    "i": 9787114005145,
    "t": "Han Wei qi che liang bei ci dian = Kha\u0306nzucha\u0306-Uighurcha\u0306 aptomobil o\u0308lchigu\u0308chliri lughiti : sinaq nuskhisi",
    "h": 1,
    "e": 0
  },
  {
    "i": 9787116000919,
    "t": "Contributions from the various organizations of Ministry of Geology and Mineral Resources, PRC : 1986",
    "h": 1,
    "e": 0
  },
  {
    "i": 9787116001046,
    "t": "Zhongguo di re wu hua tan zhuan ji",
    "h": 1,
    "e": 1
  },
  {
    "i": 9787116003569,
    "t": "\u56db\u5ddd\u4e8c\u90ce\u5c71\u5730\u533a\u5fd7\u7559\u7eaa\u5730\u5c42\u53ca\u53e4\u751f\u7269 = The Silurian stratigraphy and paleontology in Erlangshan district, Sichuan",
    "h": 1,
    "e": 1
  },
  {
    "i": 9787116005389,
    "t": "Jinzhou, Jinxi, Xingcheng jiao tong you lan tu",
    "h": 1,
    "e": 0
  },
  {
    "i": 9787117000314,
    "t": "Lei zheng ji cai",
    "h": 1,
    "e": 1
  },
  {
    "i": 9787117001670,
    "t": "Gu shang fang ji xue : gong gu shang zhuan ye yong",
    "h": 1,
    "e": 1
  },
  {
    "i": 9787117001731,
    "t": "Ku shang k'o sheng wu li hsu\u0308eh : kung ku shang chuan yeh yung",
    "h": 1,
    "e": 1
  },
  {
    "i": 9787117001748,
    "t": "Gu shang ke X xian zhen duan xue : gong gu shang zhun ye yong",
    "h": 1,
    "e": 1
  },
  {
    "i": 9787117001762,
    "t": "Zhong yi gu shang ke ge jia xue shuo : gong gu shang ke zhuan ye yong",
    "h": 1,
    "e": 1
  },
  {
    "i": 9787117002882,
    "t": "Lin chuang qie pou xue cong shu, Dou jing bu fen ce",
    "h": 1,
    "e": 1
  },
  {
    "i": 9787117002899,
    "t": "Ch'ien shui shih chien ti sheng li hsu\u0308eh yu\u0308an li ho i hsu\u0308eh wen t'i",
    "h": 1,
    "e": 1
  },
  {
    "i": 9787117003728,
    "t": "Liu xing xing chu xue re fang zhi shou ce",
    "h": 1,
    "e": 1
  },
  {
    "i": 9787117005289,
    "t": "Sheng li xue : gong hu shi zhuan ye yong",
    "h": 1,
    "e": 0
  },
  {
    "i": 9787117007405,
    "t": "Zhong hua ren min gong he guo yao dian. 1985 nian ban zeng bu ben 1987",
    "h": 1,
    "e": 1
  },
  {
    "i": 9787117008570,
    "t": "Chuxiong kashan bing zong he xing ke xue kao zha wen ji, 1984-1986 nian",
    "h": 1,
    "e": 0
  },
  {
    "i": 9787117009737,
    "t": "Bing li xue",
    "h": 1,
    "e": 1
  },
  {
    "i": 9787117009737,
    "t": "Bing li xue",
    "h": 1,
    "e": 1
  },
  {
    "i": 9787118006766,
    "t": "\u56fd\u9632\u8ba1\u91cf",
    "h": 1,
    "e": 0
  },
  {
    "i": 9787118008227,
    "t": "\u6e17\u900f\u30fb\u670d\u52a1\u30fb\u4fdd\u8bc1 : \u56fd\u9632\u79d1\u7814\u8bd5\u9a8c\u4efb\u52a1\u4e2d\u7684\u653f\u6cbb\u5de5\u4f5c\u7ecf\u9a8c\u9009\u7f16",
    "h": 1,
    "e": 0
  },
  {
    "i": 9787120003777,
    "t": "Zhongguo dian li gong ye : jin zhu fa dian zhuang ji rong liang zhao guo 1 yi qian wa = Electric power industry in China : in celebration of national installed generating capacity over 100 GW",
    "h": 1,
    "e": 1
  }
]